ausweather/__init__.py
ausweather/alphaSA_136.txt
ausweather/bom.py
ausweather/charts.py
ausweather/core.py
ausweather/database.py
ausweather/silo.py
ausweather/silo_stations.txt
ausweather-0.13.dist-info/licenses/LICENSE.md
ausweather-0.13.dist-info/METADATA
ausweather-0.13.dist-info/WHEEL
ausweather-0.13.dist-info/top_level.txt
ausweather-0.13.dist-info/RECORD
