Metadata-Version: 2.4
Name: ausweather
Version: 0.13
Summary: Python package to download Australian rainfall data from the Bureau of Meteorology via the Queensland Government's SILO Patched Point Data service
Home-page: https://github.com/kinverarity1/ausweather
Author: Kent Inverarity
Author-email: kinverarity@hotmail.com
License: MIT
Keywords: rainfall australia bom silo python data-access
Classifier: Programming Language :: Python :: 3
Classifier: Topic :: Scientific/Engineering
License-File: LICENSE.md
Requires-Dist: pandas
Requires-Dist: requests
Requires-Dist: matplotlib
Requires-Dist: scipy
Dynamic: author
Dynamic: author-email
Dynamic: classifier
Dynamic: description
Dynamic: description-content-type
Dynamic: home-page
Dynamic: keywords
Dynamic: license
Dynamic: license-file
Dynamic: requires-dist
Dynamic: summary
